MANIFEST.in
README.rst
setup.py
undead.py
undead.egg-info/PKG-INFO
undead.egg-info/SOURCES.txt
undead.egg-info/dependency_links.txt
undead.egg-info/requires.txt
undead.egg-info/top_level.txt
undead.egg-info/zip-safe