Metadata-Version: 1.0
Name: undead
Version: 0.2.0
Summary: Dead Easy UNIX Daemons!
Home-page: https://github.com/waawal/undead
Author: Daniel Waardal
Author-email: waawal@boom.ws
License: MIT
Platform: UNKNOWN
Classifier: Development Status :: 4 - Beta
Classifier: Intended Audience :: Developers
Classifier: Intended Audience :: Information Technology
Classifier: Intended Audience :: System Administrators
Classifier: License :: OSI Approved :: MIT License
Classifier: Programming Language :: Python
Classifier: Topic :: Software Development :: Libraries :: Python Modules
Classifier: Topic :: System :: Distributed Computing
Classifier: Topic :: System :: Systems Administration
